ibmos2spark/__info__.py
ibmos2spark/__init__.py
ibmos2spark/osconfig.py
ibmos2spark-1.0.1.dist-info/DESCRIPTION.rst
ibmos2spark-1.0.1.dist-info/METADATA
ibmos2spark-1.0.1.dist-info/metadata.json
ibmos2spark-1.0.1.dist-info/pbr.json
ibmos2spark-1.0.1.dist-info/RECORD
ibmos2spark-1.0.1.dist-info/top_level.txt
ibmos2spark-1.0.1.dist-info/WHEEL
