Metadata-Version: 2.0
Name: ibmos2spark
Version: 1.0.1
Summary: Helper tool to access Softlayer Object Store
Home-page: https://github.com/ibm-cds-labs/ibmos2spark
Author: gadamc
Author-email: adamcox@us.ibm.com
License: UNKNOWN
Platform: UNKNOWN
Classifier: Intended Audience :: Developers
Classifier: Natural Language :: English
Classifier: License :: OSI Approved :: Apache Software License
Classifier: Topic :: Software Development :: Libraries
Classifier: Development Status :: 5 - Production/Stable
Classifier: Programming Language :: Python
Classifier: Programming Language :: Python :: 2
Classifier: Programming Language :: Python :: 2.7
Classifier: Programming Language :: Python :: 3
Classifier: Programming Language :: Python :: 3.5
